README.rst
setup.py
defogging/__init__.py
defogging/defogging.py
defogging.egg-info/PKG-INFO
defogging.egg-info/SOURCES.txt
defogging.egg-info/dependency_links.txt
defogging.egg-info/entry_points.txt
defogging.egg-info/requires.txt
defogging.egg-info/top_level.txt
defogging.egg-info/zip-safe
defogging/core/__init__.py
defogging/core/airlight.py
defogging/core/guidedfilter.py
defogging/core/minfilter.py
defogging/core/recover.py
defogging/core/transmission.py
defogging/utils/__init__.py
defogging/utils/padding.py
defogging/core/__init__.py
defogging/core/airlight.py
defogging/core/guidedfilter.py
defogging/core/minfilter.py
defogging/core/recover.py
defogging/core/transmission.py
defogging/utils/__init__.py
defogging/utils/padding.py