Metadata-Version: 1.0
Name: defogging
Version: 0.1.7
Summary: Defogging based on Python
Home-page: https://github.com/scloudyy/Defogging
Author: scloudyy
Author-email: onecloud.shen@gmail.com
License: GPL
Keywords: python image defogging dehaze
Platform: UNKNOWN
